p2whois
